sparkles/__init__.py
sparkles/config.py
sparkles/data_utils.py
sparkles/fast_gsheet.py
sparkles/fbprophet_hacks.py
sparkles/file_utils.py
sparkles/google_sheet.py
sparkles/gsheet_compare.py
sparkles/mongo_tools.py
sparkles/parsing.py
sparkles/root_path_worker.py
sparkles/xlrd_gsheet_reader.py
sparkles-0.2.1.dist-info/METADATA
sparkles-0.2.1.dist-info/WHEEL
sparkles-0.2.1.dist-info/licenses/LICENSE
sparkles-0.2.1.dist-info/RECORD
