Metadata-Version: 2.4
Name: sparkles
Version: 0.2.1
Summary: Just utilities made by Jim Vogel
Project-URL: Homepage, https://github.com/voglster/sparkles
Project-URL: Repository, https://github.com/voglster/sparkles
Author-email: James Vogel <jim.m.vogel@gmail.com>
License: MIT
License-File: LICENSE
Classifier: License :: OSI Approved :: MIT License
Classifier: Programming Language :: Python :: 3
Classifier: Programming Language :: Python :: 3.10
Classifier: Programming Language :: Python :: 3.11
Classifier: Programming Language :: Python :: 3.12
Requires-Python: >=3.10
Requires-Dist: google-auth-oauthlib>=1.2.1
Requires-Dist: google-auth>=2.34.0
Requires-Dist: gspread>=6.1.4
Requires-Dist: loguru>=0.7.2
Requires-Dist: notifiers>=1.3.3
Requires-Dist: openpyxl>=3.1.5
Requires-Dist: python-dotenv>=1.0.1
Requires-Dist: pytz>=2024.1
Requires-Dist: requests>=2.32.3
Requires-Dist: starlette>=0.41.3
Requires-Dist: uvicorn>=0.32.1
Provides-Extra: dev
Requires-Dist: pytest-cov>=6.0.0; extra == 'dev'
Requires-Dist: pytest-watch>=4.2.0; extra == 'dev'
Requires-Dist: pytest>=8.3.4; extra == 'dev'
Requires-Dist: ruff>=0.8.4; extra == 'dev'
Provides-Extra: test
Requires-Dist: pytest-cov>=6.0.0; extra == 'test'
Requires-Dist: pytest>=8.3.4; extra == 'test'
